tea_data_file_conversion/__init__.py
tea_data_file_conversion/cli.py
tea_data_file_conversion/processor.py
tea_data_file_conversion/py.typed
tea_data_file_conversion-0.1.3.dist-info/licenses/LICENSE
tea_data_file_conversion-0.1.3.dist-info/METADATA
tea_data_file_conversion-0.1.3.dist-info/WHEEL
tea_data_file_conversion-0.1.3.dist-info/entry_points.txt
tea_data_file_conversion-0.1.3.dist-info/top_level.txt
tea_data_file_conversion-0.1.3.dist-info/RECORD
