Metadata-Version: 2.4
Name: tea-data-file-conversion
Version: 0.1.3
Summary: Fixedwidth Processor is a Python package designed to transform fixed-width text files into CSVs using dynamic YAML schema configurations.
Author-email: Mark Moreno <mamoreno@aldineisd.org>
License: MIT
Project-URL: Bug Tracker, https://github.com/markm-io/tea-data-file-conversion/issues
Project-URL: Changelog, https://github.com/markm-io/tea-data-file-conversion/blob/main/CHANGELOG.md
Project-URL: documentation, https://tea-data-file-conversion.readthedocs.io
Project-URL: repository, https://github.com/markm-io/tea-data-file-conversion
Classifier: Development Status :: 2 - Pre-Alpha
Classifier: Intended Audience :: Developers
Classifier: Natural Language :: English
Classifier: Operating System :: OS Independent
Classifier: Programming Language :: Python :: 3.9
Classifier: Programming Language :: Python :: 3.10
Classifier: Programming Language :: Python :: 3.11
Classifier: Programming Language :: Python :: 3.12
Classifier: Programming Language :: Python :: 3.13
Classifier: Topic :: Software Development :: Libraries
Requires-Python: >=3.9
License-File: LICENSE
Requires-Dist: importlib-resources>=6.5.2
Requires-Dist: pandas>=2.2.3
Requires-Dist: pyyaml>=6.0.2
Requires-Dist: rich>=10
Requires-Dist: typer<1,>=0.15
Dynamic: license-file
